[
  {
    "fipscode": "25001",
    "level": "county",
    "officeid": "G",
    "party": "GOP",
    "polid": "60668",
    "polnum": "27237",
    "precinctsreporting": 65,
    "precinctsreportingpct": 1,
    "precinctstotal": 65,
    "raceid": "22957",
    "runoff": false,
    "seatnum": null,
    "statepostal": "MA",
    "votecount": 85332,
    "votepct": 0.740916,
    "winner": false
  },
  {
    "fipscode": "25001",
    "level": "county",
    "officeid": "G",
    "party": "Dem",
    "polid": "67468",
    "polnum": "27772",
    "precinctsreporting": 65,
    "precinctsreportingpct": 1,
    "precinctstotal": 65,
    "raceid": "22957",
    "runoff": false,
    "seatnum": null,
    "statepostal": "MA",
    "votecount": 29839,
    "votepct": 0.259084,
    "winner": false
  },
  {
    "fipscode": "25003",
    "level": "county",
    "officeid": "G",
    "party": "GOP",
    "polid": "60668",
    "polnum": "27237",
    "precinctsreporting": 59,
    "precinctsreportingpct": 1,
    "precinctstotal": 59,
    "raceid": "22957",
    "runoff": false,
    "seatnum": null,
    "statepostal": "MA",
    "votecount": 28142,
    "votepct": 0.531352,
    "winner": false
  },
  {
    "fipscode": "25003",
    "level": "county",
    "officeid": "G",
    "party": "Dem",
    "polid": "67468",
    "polnum": "27772",
    "precinctsreporting": 59,
    "precinctsreportingpct": 1,
    "precinctstotal": 59,
    "raceid": "22957",
    "runoff": false,
    "seatnum": null,
    "statepostal": "MA",
    "votecount": 24821,
    "votepct": 0.468648,
    "winner": false
  },
  {
    "fipscode": "25005",
    "level": "county",
    "officeid": "G",
    "party": "GOP",
    "polid": "60668",
    "polnum": "27237",
    "precinctsreporting": 172,
    "precinctsreportingpct": 1,
    "precinctstotal": 172,
    "raceid": "22957",
    "runoff": false,
    "seatnum": null,
    "statepostal": "MA",
    "votecount": 130100,
    "votepct": 0.71023,
    "winner": false
  },
  {
    "fipscode": "25005",
    "level": "county",
    "officeid": "G",
    "party": "Dem",
    "polid": "67468",
    "polnum": "27772",
    "precinctsreporting": 172,
    "precinctsreportingpct": 1,
    "precinctstotal": 172,
    "raceid": "22957",
    "runoff": false,
    "seatnum": null,
    "statepostal": "MA",
    "votecount": 53080,
    "votepct": 0.28977,
    "winner": false
  },
  {
    "fipscode": "25007",
    "level": "county",
    "officeid": "G",
    "party": "GOP",
    "polid": "60668",
    "polnum": "27237",
    "precinctsreporting": 7,
    "precinctsreportingpct": 1,
    "precinctstotal": 7,
    "raceid": "22957",
    "runoff": false,
    "seatnum": null,
    "statepostal": "MA",
    "votecount": 5543,
    "votepct": 0.555188,
    "winner": false
  },
  {
    "fipscode": "25007",
    "level": "county",
    "officeid": "G",
    "party": "Dem",
    "polid": "67468",
    "polnum": "27772",
    "precinctsreporting": 7,
    "precinctsreportingpct": 1,
    "precinctstotal": 7,
    "raceid": "22957",
    "runoff": false,
    "seatnum": null,
    "statepostal": "MA",
    "votecount": 4441,
    "votepct": 0.444812,
    "winner": false
  },
  {
    "fipscode": "25009",
    "level": "county",
    "officeid": "G",
    "party": "GOP",
    "polid": "60668",
    "polnum": "27237",
    "precinctsreporting": 239,
    "precinctsreportingpct": 1,
    "precinctstotal": 239,
    "raceid": "22957",
    "runoff": false,
    "seatnum": null,
    "statepostal": "MA",
    "votecount": 219403,
    "votepct": 0.718315,
    "winner": false
  },
  {
    "fipscode": "25009",
    "level": "county",
    "officeid": "G",
    "party": "Dem",
    "polid": "67468",
    "polnum": "27772",
    "precinctsreporting": 239,
    "precinctsreportingpct": 1,
    "precinctstotal": 239,
    "raceid": "22957",
    "runoff": false,
    "seatnum": null,
    "statepostal": "MA",
    "votecount": 86038,
    "votepct": 0.281685,
    "winner": false
  },
  {
    "fipscode": "25011",
    "level": "county",
    "officeid": "G",
    "party": "GOP",
    "polid": "60668",
    "polnum": "27237",
    "precinctsreporting": 40,
    "precinctsreportingpct": 1,
    "precinctstotal": 40,
    "raceid": "22957",
    "runoff": false,
    "seatnum": null,
    "statepostal": "MA",
    "votecount": 18220,
    "votepct": 0.55751,
    "winner": false
  },
  {
    "fipscode": "25011",
    "level": "county",
    "officeid": "G",
    "party": "Dem",
    "polid": "67468",
    "polnum": "27772",
    "precinctsreporting": 40,
    "precinctsreportingpct": 1,
    "precinctstotal": 40,
    "raceid": "22957",
    "runoff": false,
    "seatnum": null,
    "statepostal": "MA",
    "votecount": 14461,
    "votepct": 0.44249,
    "winner": false
  },
  {
    "fipscode": "25013",
    "level": "county",
    "officeid": "G",
    "party": "GOP",
    "polid": "60668",
    "polnum": "27237",
    "precinctsreporting": 166,
    "precinctsreportingpct": 1,
    "precinctstotal": 166,
    "raceid": "22957",
    "runoff": false,
    "seatnum": null,
    "statepostal": "MA",
    "votecount": 109698,
    "votepct": 0.715923,
    "winner": false
  },
  {
    "fipscode": "25013",
    "level": "county",
    "officeid": "G",
    "party": "Dem",
    "polid": "67468",
    "polnum": "27772",
    "precinctsreporting": 166,
    "precinctsreportingpct": 1,
    "precinctstotal": 166,
    "raceid": "22957",
    "runoff": false,
    "seatnum": null,
    "statepostal": "MA",
    "votecount": 43528,
    "votepct": 0.284077,
    "winner": false
  },
  {
    "fipscode": "25015",
    "level": "county",
    "officeid": "G",
    "party": "GOP",
    "polid": "60668",
    "polnum": "27237",
    "precinctsreporting": 56,
    "precinctsreportingpct": 1,
    "precinctstotal": 56,
    "raceid": "22957",
    "runoff": false,
    "seatnum": null,
    "statepostal": "MA",
    "votecount": 37086,
    "votepct": 0.533811,
    "winner": false
  },
  {
    "fipscode": "25015",
    "level": "county",
    "officeid": "G",
    "party": "Dem",
    "polid": "67468",
    "polnum": "27772",
    "precinctsreporting": 56,
    "precinctsreportingpct": 1,
    "precinctstotal": 56,
    "raceid": "22957",
    "runoff": false,
    "seatnum": null,
    "statepostal": "MA",
    "votecount": 32388,
    "votepct": 0.466189,
    "winner": false
  },
  {
    "fipscode": "25017",
    "level": "county",
    "officeid": "G",
    "party": "GOP",
    "polid": "60668",
    "polnum": "27237",
    "precinctsreporting": 474,
    "precinctsreportingpct": 1,
    "precinctstotal": 474,
    "raceid": "22957",
    "runoff": false,
    "seatnum": null,
    "statepostal": "MA",
    "votecount": 407781,
    "votepct": 0.6275,
    "winner": false
  },
  {
    "fipscode": "25017",
    "level": "county",
    "officeid": "G",
    "party": "Dem",
    "polid": "67468",
    "polnum": "27772",
    "precinctsreporting": 474,
    "precinctsreportingpct": 1,
    "precinctstotal": 474,
    "raceid": "22957",
    "runoff": false,
    "seatnum": null,
    "statepostal": "MA",
    "votecount": 242069,
    "votepct": 0.3725,
    "winner": false
  },
  {
    "fipscode": "25019",
    "level": "county",
    "officeid": "G",
    "party": "GOP",
    "polid": "60668",
    "polnum": "27237",
    "precinctsreporting": 1,
    "precinctsreportingpct": 1,
    "precinctstotal": 1,
    "raceid": "22957",
    "runoff": false,
    "seatnum": null,
    "statepostal": "MA",
    "votecount": 3029,
    "votepct": 0.57259,
    "winner": false
  },
  {
    "fipscode": "25019",
    "level": "county",
    "officeid": "G",
    "party": "Dem",
    "polid": "67468",
    "polnum": "27772",
    "precinctsreporting": 1,
    "precinctsreportingpct": 1,
    "precinctstotal": 1,
    "raceid": "22957",
    "runoff": false,
    "seatnum": null,
    "statepostal": "MA",
    "votecount": 2261,
    "votepct": 0.42741,
    "winner": false
  },
  {
    "fipscode": "25021",
    "level": "county",
    "officeid": "G",
    "party": "GOP",
    "polid": "60668",
    "polnum": "27237",
    "precinctsreporting": 211,
    "precinctsreportingpct": 1,
    "precinctstotal": 211,
    "raceid": "22957",
    "runoff": false,
    "seatnum": null,
    "statepostal": "MA",
    "votecount": 208133,
    "votepct": 0.694501,
    "winner": false
  },
  {
    "fipscode": "25021",
    "level": "county",
    "officeid": "G",
    "party": "Dem",
    "polid": "67468",
    "polnum": "27772",
    "precinctsreporting": 211,
    "precinctsreportingpct": 1,
    "precinctstotal": 211,
    "raceid": "22957",
    "runoff": false,
    "seatnum": null,
    "statepostal": "MA",
    "votecount": 91554,
    "votepct": 0.305499,
    "winner": false
  },
  {
    "fipscode": "25023",
    "level": "county",
    "officeid": "G",
    "party": "GOP",
    "polid": "60668",
    "polnum": "27237",
    "precinctsreporting": 143,
    "precinctsreportingpct": 1,
    "precinctstotal": 143,
    "raceid": "22957",
    "runoff": false,
    "seatnum": null,
    "statepostal": "MA",
    "votecount": 163236,
    "votepct": 0.752299,
    "winner": false
  },
  {
    "fipscode": "25023",
    "level": "county",
    "officeid": "G",
    "party": "Dem",
    "polid": "67468",
    "polnum": "27772",
    "precinctsreporting": 143,
    "precinctsreportingpct": 1,
    "precinctstotal": 143,
    "raceid": "22957",
    "runoff": false,
    "seatnum": null,
    "statepostal": "MA",
    "votecount": 53747,
    "votepct": 0.247701,
    "winner": false
  },
  {
    "fipscode": "25025",
    "level": "county",
    "officeid": "G",
    "party": "GOP",
    "polid": "60668",
    "polnum": "27237",
    "precinctsreporting": 298,
    "precinctsreportingpct": 1,
    "precinctstotal": 298,
    "raceid": "22957",
    "runoff": false,
    "seatnum": null,
    "statepostal": "MA",
    "votecount": 124210,
    "votepct": 0.507815,
    "winner": false
  },
  {
    "fipscode": "25025",
    "level": "county",
    "officeid": "G",
    "party": "Dem",
    "polid": "67468",
    "polnum": "27772",
    "precinctsreporting": 298,
    "precinctsreportingpct": 1,
    "precinctstotal": 298,
    "raceid": "22957",
    "runoff": false,
    "seatnum": null,
    "statepostal": "MA",
    "votecount": 120387,
    "votepct": 0.492185,
    "winner": false
  },
  {
    "fipscode": "25027",
    "level": "county",
    "officeid": "G",
    "party": "GOP",
    "polid": "60668",
    "polnum": "27237",
    "precinctsreporting": 242,
    "precinctsreportingpct": 1,
    "precinctstotal": 242,
    "raceid": "22957",
    "runoff": false,
    "seatnum": null,
    "statepostal": "MA",
    "votecount": 230217,
    "votepct": 0.751381,
    "winner": false
  },
  {
    "fipscode": "25027",
    "level": "county",
    "officeid": "G",
    "party": "Dem",
    "polid": "67468",
    "polnum": "27772",
    "precinctsreporting": 242,
    "precinctsreportingpct": 1,
    "precinctstotal": 242,
    "raceid": "22957",
    "runoff": false,
    "seatnum": null,
    "statepostal": "MA",
    "votecount": 76175,
    "votepct": 0.248619,
    "winner": false
  },
  {
    "fipscode": "25003",
    "level": "county",
    "officeid": "H",
    "party": "Dem",
    "polid": "882",
    "polnum": "22028",
    "precinctsreporting": 0,
    "precinctsreportingpct": 0,
    "precinctstotal": 0,
    "raceid": "22947",
    "runoff": false,
    "seatnum": "1",
    "statepostal": "MA",
    "votecount": 0,
    "votepct": 0,
    "winner": false
  },
  {
    "fipscode": "25011",
    "level": "county",
    "officeid": "H",
    "party": "Dem",
    "polid": "882",
    "polnum": "22028",
    "precinctsreporting": 0,
    "precinctsreportingpct": 0,
    "precinctstotal": 0,
    "raceid": "22947",
    "runoff": false,
    "seatnum": "1",
    "statepostal": "MA",
    "votecount": 0,
    "votepct": 0,
    "winner": false
  },
  {
    "fipscode": "25013",
    "level": "county",
    "officeid": "H",
    "party": "Dem",
    "polid": "882",
    "polnum": "22028",
    "precinctsreporting": 0,
    "precinctsreportingpct": 0,
    "precinctstotal": 0,
    "raceid": "22947",
    "runoff": false,
    "seatnum": "1",
    "statepostal": "MA",
    "votecount": 0,
    "votepct": 0,
    "winner": false
  },
  {
    "fipscode": "25015",
    "level": "county",
    "officeid": "H",
    "party": "Dem",
    "polid": "882",
    "polnum": "22028",
    "precinctsreporting": 0,
    "precinctsreportingpct": 0,
    "precinctstotal": 0,
    "raceid": "22947",
    "runoff": false,
    "seatnum": "1",
    "statepostal": "MA",
    "votecount": 0,
    "votepct": 0,
    "winner": false
  },
  {
    "fipscode": "25027",
    "level": "county",
    "officeid": "H",
    "party": "Dem",
    "polid": "882",
    "polnum": "22028",
    "precinctsreporting": 0,
    "precinctsreportingpct": 0,
    "precinctstotal": 0,
    "raceid": "22947",
    "runoff": false,
    "seatnum": "1",
    "statepostal": "MA",
    "votecount": 0,
    "votepct": 0,
    "winner": false
  },
  {
    "fipscode": "25011",
    "level": "county",
    "officeid": "H",
    "party": "Dem",
    "polid": "883",
    "polnum": "23734",
    "precinctsreporting": 28,
    "precinctsreportingpct": 1,
    "precinctstotal": 28,
    "raceid": "22948",
    "runoff": false,
    "seatnum": "2",
    "statepostal": "MA",
    "votecount": 19227,
    "votepct": 0.771085,
    "winner": false
  },
  {
    "fipscode": "25011",
    "level": "county",
    "officeid": "H",
    "party": "GOP",
    "polid": "67470",
    "polnum": "27779",
    "precinctsreporting": 28,
    "precinctsreportingpct": 1,
    "precinctstotal": 28,
    "raceid": "22948",
    "runoff": false,
    "seatnum": "2",
    "statepostal": "MA",
    "votecount": 5708,
    "votepct": 0.228915,
    "winner": false
  },
  {
    "fipscode": "25013",
    "level": "county",
    "officeid": "H",
    "party": "Dem",
    "polid": "883",
    "polnum": "23734",
    "precinctsreporting": 1,
    "precinctsreportingpct": 1,
    "precinctstotal": 1,
    "raceid": "22948",
    "runoff": false,
    "seatnum": "2",
    "statepostal": "MA",
    "votecount": 74,
    "votepct": 0.521127,
    "winner": false
  },
  {
    "fipscode": "25013",
    "level": "county",
    "officeid": "H",
    "party": "GOP",
    "polid": "67470",
    "polnum": "27779",
    "precinctsreporting": 1,
    "precinctsreportingpct": 1,
    "precinctstotal": 1,
    "raceid": "22948",
    "runoff": false,
    "seatnum": "2",
    "statepostal": "MA",
    "votecount": 68,
    "votepct": 0.478873,
    "winner": false
  },
  {
    "fipscode": "25015",
    "level": "county",
    "officeid": "H",
    "party": "Dem",
    "polid": "883",
    "polnum": "23734",
    "precinctsreporting": 34,
    "precinctsreportingpct": 1,
    "precinctstotal": 34,
    "raceid": "22948",
    "runoff": false,
    "seatnum": "2",
    "statepostal": "MA",
    "votecount": 33933,
    "votepct": 0.827998,
    "winner": false
  },
  {
    "fipscode": "25015",
    "level": "county",
    "officeid": "H",
    "party": "GOP",
    "polid": "67470",
    "polnum": "27779",
    "precinctsreporting": 34,
    "precinctsreportingpct": 1,
    "precinctstotal": 34,
    "raceid": "22948",
    "runoff": false,
    "seatnum": "2",
    "statepostal": "MA",
    "votecount": 7049,
    "votepct": 0.172002,
    "winner": false
  },
  {
    "fipscode": "25021",
    "level": "county",
    "officeid": "H",
    "party": "Dem",
    "polid": "883",
    "polnum": "23734",
    "precinctsreporting": 2,
    "precinctsreportingpct": 1,
    "precinctstotal": 2,
    "raceid": "22948",
    "runoff": false,
    "seatnum": "2",
    "statepostal": "MA",
    "votecount": 821,
    "votepct": 0.557745,
    "winner": false
  },
  {
    "fipscode": "25021",
    "level": "county",
    "officeid": "H",
    "party": "GOP",
    "polid": "67470",
    "polnum": "27779",
    "precinctsreporting": 2,
    "precinctsreportingpct": 1,
    "precinctstotal": 2,
    "raceid": "22948",
    "runoff": false,
    "seatnum": "2",
    "statepostal": "MA",
    "votecount": 651,
    "votepct": 0.442255,
    "winner": false
  },
  {
    "fipscode": "25027",
    "level": "county",
    "officeid": "H",
    "party": "Dem",
    "polid": "883",
    "polnum": "23734",
    "precinctsreporting": 170,
    "precinctsreportingpct": 1,
    "precinctstotal": 170,
    "raceid": "22948",
    "runoff": false,
    "seatnum": "2",
    "statepostal": "MA",
    "votecount": 136074,
    "votepct": 0.631223,
    "winner": false
  },
  {
    "fipscode": "25027",
    "level": "county",
    "officeid": "H",
    "party": "GOP",
    "polid": "67470",
    "polnum": "27779",
    "precinctsreporting": 170,
    "precinctsreportingpct": 1,
    "precinctstotal": 170,
    "raceid": "22948",
    "runoff": false,
    "seatnum": "2",
    "statepostal": "MA",
    "votecount": 79498,
    "votepct": 0.368777,
    "winner": false
  },
  {
    "fipscode": "25009",
    "level": "county",
    "officeid": "H",
    "party": "Dem",
    "polid": "67479",
    "polnum": "27788",
    "precinctsreporting": 64,
    "precinctsreportingpct": 1,
    "precinctstotal": 64,
    "raceid": "22949",
    "runoff": false,
    "seatnum": "3",
    "statepostal": "MA",
    "votecount": 42007,
    "votepct": 0.62963,
    "winner": false
  },
  {
    "fipscode": "25009",
    "level": "county",
    "officeid": "H",
    "party": "GOP",
    "polid": "67491",
    "polnum": "27789",
    "precinctsreporting": 64,
    "precinctsreportingpct": 1,
    "precinctstotal": 64,
    "raceid": "22949",
    "runoff": false,
    "seatnum": "3",
    "statepostal": "MA",
    "votecount": 22056,
    "votepct": 0.33059,
    "winner": false
  },
  {
    "fipscode": "25009",
    "level": "county",
    "officeid": "H",
    "party": "Ind",
    "polid": "67867",
    "polnum": "27958",
    "precinctsreporting": 64,
    "precinctsreportingpct": 1,
    "precinctstotal": 64,
    "raceid": "22949",
    "runoff": false,
    "seatnum": "3",
    "statepostal": "MA",
    "votecount": 2654,
    "votepct": 0.03978,
    "winner": false
  },
  {
    "fipscode": "25017",
    "level": "county",
    "officeid": "H",
    "party": "Dem",
    "polid": "67479",
    "polnum": "27788",
    "precinctsreporting": 120,
    "precinctsreportingpct": 1,
    "precinctstotal": 120,
    "raceid": "22949",
    "runoff": false,
    "seatnum": "3",
    "statepostal": "MA",
    "votecount": 102315,
    "votepct": 0.636315,
    "winner": false
  },
  {
    "fipscode": "25017",
    "level": "county",
    "officeid": "H",
    "party": "GOP",
    "polid": "67491",
    "polnum": "27789",
    "precinctsreporting": 120,
    "precinctsreportingpct": 1,
    "precinctstotal": 120,
    "raceid": "22949",
    "runoff": false,
    "seatnum": "3",
    "statepostal": "MA",
    "votecount": 51148,
    "votepct": 0.318098,
    "winner": false
  },
  {
    "fipscode": "25017",
    "level": "county",
    "officeid": "H",
    "party": "Ind",
    "polid": "67867",
    "polnum": "27958",
    "precinctsreporting": 120,
    "precinctsreportingpct": 1,
    "precinctstotal": 120,
    "raceid": "22949",
    "runoff": false,
    "seatnum": "3",
    "statepostal": "MA",
    "votecount": 7330,
    "votepct": 0.045587,
    "winner": false
  },
  {
    "fipscode": "25027",
    "level": "county",
    "officeid": "H",
    "party": "Dem",
    "polid": "67479",
    "polnum": "27788",
    "precinctsreporting": 41,
    "precinctsreportingpct": 1,
    "precinctstotal": 41,
    "raceid": "22949",
    "runoff": false,
    "seatnum": "3",
    "statepostal": "MA",
    "votecount": 27041,
    "votepct": 0.550958,
    "winner": false
  },
  {
    "fipscode": "25027",
    "level": "county",
    "officeid": "H",
    "party": "GOP",
    "polid": "67491",
    "polnum": "27789",
    "precinctsreporting": 41,
    "precinctsreportingpct": 1,
    "precinctstotal": 41,
    "raceid": "22949",
    "runoff": false,
    "seatnum": "3",
    "statepostal": "MA",
    "votecount": 19549,
    "votepct": 0.398309,
    "winner": false
  },
  {
    "fipscode": "25027",
    "level": "county",
    "officeid": "H",
    "party": "Ind",
    "polid": "67867",
    "polnum": "27958",
    "precinctsreporting": 41,
    "precinctsreportingpct": 1,
    "precinctstotal": 41,
    "raceid": "22949",
    "runoff": false,
    "seatnum": "3",
    "statepostal": "MA",
    "votecount": 2490,
    "votepct": 0.050733,
    "winner": false
  },
  {
    "fipscode": "25005",
    "level": "county",
    "officeid": "H",
    "party": "Dem",
    "polid": "60122",
    "polnum": "22038",
    "precinctsreporting": 0,
    "precinctsreportingpct": 0,
    "precinctstotal": 0,
    "raceid": "22950",
    "runoff": false,
    "seatnum": "4",
    "statepostal": "MA",
    "votecount": 0,
    "votepct": 0,
    "winner": false
  },
  {
    "fipscode": "25017",
    "level": "county",
    "officeid": "H",
    "party": "Dem",
    "polid": "60122",
    "polnum": "22038",
    "precinctsreporting": 0,
    "precinctsreportingpct": 0,
    "precinctstotal": 0,
    "raceid": "22950",
    "runoff": false,
    "seatnum": "4",
    "statepostal": "MA",
    "votecount": 0,
    "votepct": 0,
    "winner": false
  },
  {
    "fipscode": "25021",
    "level": "county",
    "officeid": "H",
    "party": "Dem",
    "polid": "60122",
    "polnum": "22038",
    "precinctsreporting": 0,
    "precinctsreportingpct": 0,
    "precinctstotal": 0,
    "raceid": "22950",
    "runoff": false,
    "seatnum": "4",
    "statepostal": "MA",
    "votecount": 0,
    "votepct": 0,
    "winner": false
  },
  {
    "fipscode": "25023",
    "level": "county",
    "officeid": "H",
    "party": "Dem",
    "polid": "60122",
    "polnum": "22038",
    "precinctsreporting": 0,
    "precinctsreportingpct": 0,
    "precinctstotal": 0,
    "raceid": "22950",
    "runoff": false,
    "seatnum": "4",
    "statepostal": "MA",
    "votecount": 0,
    "votepct": 0,
    "winner": false
  },
  {
    "fipscode": "25027",
    "level": "county",
    "officeid": "H",
    "party": "Dem",
    "polid": "60122",
    "polnum": "22038",
    "precinctsreporting": 0,
    "precinctsreportingpct": 0,
    "precinctstotal": 0,
    "raceid": "22950",
    "runoff": false,
    "seatnum": "4",
    "statepostal": "MA",
    "votecount": 0,
    "votepct": 0,
    "winner": false
  },
  {
    "fipscode": "25009",
    "level": "county",
    "officeid": "H",
    "party": "Dem",
    "polid": "63945",
    "polnum": "27247",
    "precinctsreporting": 175,
    "precinctsreportingpct": 1,
    "precinctstotal": 175,
    "raceid": "22952",
    "runoff": false,
    "seatnum": "6",
    "statepostal": "MA",
    "votecount": 159995,
    "votepct": 0.667583,
    "winner": false
  },
  {
    "fipscode": "25009",
    "level": "county",
    "officeid": "H",
    "party": "GOP",
    "polid": "67483",
    "polnum": "27793",
    "precinctsreporting": 175,
    "precinctsreportingpct": 1,
    "precinctstotal": 175,
    "raceid": "22952",
    "runoff": false,
    "seatnum": "6",
    "statepostal": "MA",
    "votecount": 71937,
    "votepct": 0.300159,
    "winner": false
  },
  {
    "fipscode": "25009",
    "level": "county",
    "officeid": "H",
    "party": "Ind",
    "polid": "49144",
    "polnum": "27966",
    "precinctsreporting": 175,
    "precinctsreportingpct": 1,
    "precinctstotal": 175,
    "raceid": "22952",
    "runoff": false,
    "seatnum": "6",
    "statepostal": "MA",
    "votecount": 7731,
    "votepct": 0.032258,
    "winner": false
  },
  {
    "fipscode": "25017",
    "level": "county",
    "officeid": "H",
    "party": "Dem",
    "polid": "63945",
    "polnum": "27247",
    "precinctsreporting": 55,
    "precinctsreportingpct": 1,
    "precinctstotal": 55,
    "raceid": "22952",
    "runoff": false,
    "seatnum": "6",
    "statepostal": "MA",
    "votecount": 56287,
    "votepct": 0.61021,
    "winner": false
  },
  {
    "fipscode": "25017",
    "level": "county",
    "officeid": "H",
    "party": "GOP",
    "polid": "67483",
    "polnum": "27793",
    "precinctsreporting": 55,
    "precinctsreportingpct": 1,
    "precinctstotal": 55,
    "raceid": "22952",
    "runoff": false,
    "seatnum": "6",
    "statepostal": "MA",
    "votecount": 32442,
    "votepct": 0.351705,
    "winner": false
  },
  {
    "fipscode": "25017",
    "level": "county",
    "officeid": "H",
    "party": "Ind",
    "polid": "49144",
    "polnum": "27966",
    "precinctsreporting": 55,
    "precinctsreportingpct": 1,
    "precinctstotal": 55,
    "raceid": "22952",
    "runoff": false,
    "seatnum": "6",
    "statepostal": "MA",
    "votecount": 3513,
    "votepct": 0.038085,
    "winner": false
  },
  {
    "fipscode": "25017",
    "level": "county",
    "officeid": "H",
    "party": "Dem",
    "polid": "67484",
    "polnum": "27748",
    "precinctsreporting": 0,
    "precinctsreportingpct": 0,
    "precinctstotal": 0,
    "raceid": "22953",
    "runoff": false,
    "seatnum": "7",
    "statepostal": "MA",
    "votecount": 0,
    "votepct": 0,
    "winner": false
  },
  {
    "fipscode": "25021",
    "level": "county",
    "officeid": "H",
    "party": "Dem",
    "polid": "67484",
    "polnum": "27748",
    "precinctsreporting": 0,
    "precinctsreportingpct": 0,
    "precinctstotal": 0,
    "raceid": "22953",
    "runoff": false,
    "seatnum": "7",
    "statepostal": "MA",
    "votecount": 0,
    "votepct": 0,
    "winner": false
  },
  {
    "fipscode": "25025",
    "level": "county",
    "officeid": "H",
    "party": "Dem",
    "polid": "67484",
    "polnum": "27748",
    "precinctsreporting": 0,
    "precinctsreportingpct": 0,
    "precinctstotal": 0,
    "raceid": "22953",
    "runoff": false,
    "seatnum": "7",
    "statepostal": "MA",
    "votecount": 0,
    "votepct": 0,
    "winner": false
  },
  {
    "fipscode": "25005",
    "level": "county",
    "officeid": "H",
    "party": "Dem",
    "polid": "890",
    "polnum": "23422",
    "precinctsreporting": 0,
    "precinctsreportingpct": 0,
    "precinctstotal": 0,
    "raceid": "22954",
    "runoff": false,
    "seatnum": "8",
    "statepostal": "MA",
    "votecount": 0,
    "votepct": 0,
    "winner": false
  },
  {
    "fipscode": "25021",
    "level": "county",
    "officeid": "H",
    "party": "Dem",
    "polid": "890",
    "polnum": "23422",
    "precinctsreporting": 0,
    "precinctsreportingpct": 0,
    "precinctstotal": 0,
    "raceid": "22954",
    "runoff": false,
    "seatnum": "8",
    "statepostal": "MA",
    "votecount": 0,
    "votepct": 0,
    "winner": false
  },
  {
    "fipscode": "25023",
    "level": "county",
    "officeid": "H",
    "party": "Dem",
    "polid": "890",
    "polnum": "23422",
    "precinctsreporting": 0,
    "precinctsreportingpct": 0,
    "precinctstotal": 0,
    "raceid": "22954",
    "runoff": false,
    "seatnum": "8",
    "statepostal": "MA",
    "votecount": 0,
    "votepct": 0,
    "winner": false
  },
  {
    "fipscode": "25025",
    "level": "county",
    "officeid": "H",
    "party": "Dem",
    "polid": "890",
    "polnum": "23422",
    "precinctsreporting": 0,
    "precinctsreportingpct": 0,
    "precinctstotal": 0,
    "raceid": "22954",
    "runoff": false,
    "seatnum": "8",
    "statepostal": "MA",
    "votecount": 0,
    "votepct": 0,
    "winner": false
  },
  {
    "fipscode": "25001",
    "level": "county",
    "officeid": "H",
    "party": "Dem",
    "polid": "22757",
    "polnum": "22121",
    "precinctsreporting": 65,
    "precinctsreportingpct": 1,
    "precinctstotal": 65,
    "raceid": "23865",
    "runoff": false,
    "seatnum": "9",
    "statepostal": "MA",
    "votecount": 71723,
    "votepct": 0.612577,
    "winner": false
  },
  {
    "fipscode": "25001",
    "level": "county",
    "officeid": "H",
    "party": "GOP",
    "polid": "67487",
    "polnum": "27796",
    "precinctsreporting": 65,
    "precinctsreportingpct": 1,
    "precinctstotal": 65,
    "raceid": "23865",
    "runoff": false,
    "seatnum": "9",
    "statepostal": "MA",
    "votecount": 45361,
    "votepct": 0.387423,
    "winner": false
  },
  {
    "fipscode": "25005",
    "level": "county",
    "officeid": "H",
    "party": "Dem",
    "polid": "22757",
    "polnum": "22121",
    "precinctsreporting": 75,
    "precinctsreportingpct": 1,
    "precinctstotal": 75,
    "raceid": "23865",
    "runoff": false,
    "seatnum": "9",
    "statepostal": "MA",
    "votecount": 38971,
    "votepct": 0.643213,
    "winner": false
  },
  {
    "fipscode": "25005",
    "level": "county",
    "officeid": "H",
    "party": "GOP",
    "polid": "67487",
    "polnum": "27796",
    "precinctsreporting": 75,
    "precinctsreportingpct": 1,
    "precinctstotal": 75,
    "raceid": "23865",
    "runoff": false,
    "seatnum": "9",
    "statepostal": "MA",
    "votecount": 21617,
    "votepct": 0.356787,
    "winner": false
  },
  {
    "fipscode": "25007",
    "level": "county",
    "officeid": "H",
    "party": "Dem",
    "polid": "22757",
    "polnum": "22121",
    "precinctsreporting": 7,
    "precinctsreportingpct": 1,
    "precinctstotal": 7,
    "raceid": "23865",
    "runoff": false,
    "seatnum": "9",
    "statepostal": "MA",
    "votecount": 7880,
    "votepct": 0.788552,
    "winner": false
  },
  {
    "fipscode": "25007",
    "level": "county",
    "officeid": "H",
    "party": "GOP",
    "polid": "67487",
    "polnum": "27796",
    "precinctsreporting": 7,
    "precinctsreportingpct": 1,
    "precinctstotal": 7,
    "raceid": "23865",
    "runoff": false,
    "seatnum": "9",
    "statepostal": "MA",
    "votecount": 2113,
    "votepct": 0.211448,
    "winner": false
  },
  {
    "fipscode": "25019",
    "level": "county",
    "officeid": "H",
    "party": "Dem",
    "polid": "22757",
    "polnum": "22121",
    "precinctsreporting": 1,
    "precinctsreportingpct": 1,
    "precinctstotal": 1,
    "raceid": "23865",
    "runoff": false,
    "seatnum": "9",
    "statepostal": "MA",
    "votecount": 3778,
    "votepct": 0.713638,
    "winner": false
  },
  {
    "fipscode": "25019",
    "level": "county",
    "officeid": "H",
    "party": "GOP",
    "polid": "67487",
    "polnum": "27796",
    "precinctsreporting": 1,
    "precinctsreportingpct": 1,
    "precinctstotal": 1,
    "raceid": "23865",
    "runoff": false,
    "seatnum": "9",
    "statepostal": "MA",
    "votecount": 1516,
    "votepct": 0.286362,
    "winner": false
  },
  {
    "fipscode": "25023",
    "level": "county",
    "officeid": "H",
    "party": "Dem",
    "polid": "22757",
    "polnum": "22121",
    "precinctsreporting": 74,
    "precinctsreportingpct": 1,
    "precinctstotal": 74,
    "raceid": "23865",
    "runoff": false,
    "seatnum": "9",
    "statepostal": "MA",
    "votecount": 67861,
    "votepct": 0.531501,
    "winner": false
  },
  {
    "fipscode": "25023",
    "level": "county",
    "officeid": "H",
    "party": "GOP",
    "polid": "67487",
    "polnum": "27796",
    "precinctsreporting": 74,
    "precinctsreportingpct": 1,
    "precinctstotal": 74,
    "raceid": "23865",
    "runoff": false,
    "seatnum": "9",
    "statepostal": "MA",
    "votecount": 59817,
    "votepct": 0.468499,
    "winner": false
  },
  {
    "fipscode": "25017",
    "level": "county",
    "officeid": "H",
    "party": "Dem",
    "polid": "63056",
    "polnum": "26777",
    "precinctsreporting": 213,
    "precinctsreportingpct": 1,
    "precinctstotal": 213,
    "raceid": "24356",
    "runoff": false,
    "seatnum": "5",
    "statepostal": "MA",
    "votecount": 215583,
    "votepct": 0.765171,
    "winner": false
  },
  {
    "fipscode": "25017",
    "level": "county",
    "officeid": "H",
    "party": "GOP",
    "polid": "67481",
    "polnum": "27791",
    "precinctsreporting": 213,
    "precinctsreportingpct": 1,
    "precinctstotal": 213,
    "raceid": "24356",
    "runoff": false,
    "seatnum": "5",
    "statepostal": "MA",
    "votecount": 66162,
    "votepct": 0.234829,
    "winner": false
  },
  {
    "fipscode": "25025",
    "level": "county",
    "officeid": "H",
    "party": "Dem",
    "polid": "63056",
    "polnum": "26777",
    "precinctsreporting": 27,
    "precinctsreportingpct": 1,
    "precinctstotal": 27,
    "raceid": "24356",
    "runoff": false,
    "seatnum": "5",
    "statepostal": "MA",
    "votecount": 13916,
    "votepct": 0.690244,
    "winner": false
  },
  {
    "fipscode": "25025",
    "level": "county",
    "officeid": "H",
    "party": "GOP",
    "polid": "67481",
    "polnum": "27791",
    "precinctsreporting": 27,
    "precinctsreportingpct": 1,
    "precinctstotal": 27,
    "raceid": "24356",
    "runoff": false,
    "seatnum": "5",
    "statepostal": "MA",
    "votecount": 6245,
    "votepct": 0.309756,
    "winner": false
  },
  {
    "fipscode": "25027",
    "level": "county",
    "officeid": "H",
    "party": "Dem",
    "polid": "63056",
    "polnum": "26777",
    "precinctsreporting": 3,
    "precinctsreportingpct": 1,
    "precinctstotal": 3,
    "raceid": "24356",
    "runoff": false,
    "seatnum": "5",
    "statepostal": "MA",
    "votecount": 3253,
    "votepct": 0.652689,
    "winner": false
  },
  {
    "fipscode": "25027",
    "level": "county",
    "officeid": "H",
    "party": "GOP",
    "polid": "67481",
    "polnum": "27791",
    "precinctsreporting": 3,
    "precinctsreportingpct": 1,
    "precinctstotal": 3,
    "raceid": "24356",
    "runoff": false,
    "seatnum": "5",
    "statepostal": "MA",
    "votecount": 1731,
    "votepct": 0.347311,
    "winner": false
  },
  {
    "fipscode": "25001",
    "level": "county",
    "officeid": "S",
    "party": "Dem",
    "polid": "62244",
    "polnum": "27010",
    "precinctsreporting": 65,
    "precinctsreportingpct": 1,
    "precinctstotal": 65,
    "raceid": "24012",
    "runoff": false,
    "seatnum": null,
    "statepostal": "MA",
    "votecount": 62151,
    "votepct": 0.529553,
    "winner": false
  },
  {
    "fipscode": "25001",
    "level": "county",
    "officeid": "S",
    "party": "GOP",
    "polid": "67466",
    "polnum": "26735",
    "precinctsreporting": 65,
    "precinctsreportingpct": 1,
    "precinctstotal": 65,
    "raceid": "24012",
    "runoff": false,
    "seatnum": null,
    "statepostal": "MA",
    "votecount": 51602,
    "votepct": 0.439671,
    "winner": false
  },
  {
    "fipscode": "25001",
    "level": "county",
    "officeid": "S",
    "party": "Ind",
    "polid": "67866",
    "polnum": "27962",
    "precinctsreporting": 65,
    "precinctsreportingpct": 1,
    "precinctstotal": 65,
    "raceid": "24012",
    "runoff": false,
    "seatnum": null,
    "statepostal": "MA",
    "votecount": 3612,
    "votepct": 0.030776,
    "winner": false
  },
  {
    "fipscode": "25003",
    "level": "county",
    "officeid": "S",
    "party": "Dem",
    "polid": "62244",
    "polnum": "27010",
    "precinctsreporting": 59,
    "precinctsreportingpct": 1,
    "precinctstotal": 59,
    "raceid": "24012",
    "runoff": false,
    "seatnum": null,
    "statepostal": "MA",
    "votecount": 38622,
    "votepct": 0.720466,
    "winner": false
  },
  {
    "fipscode": "25003",
    "level": "county",
    "officeid": "S",
    "party": "GOP",
    "polid": "67466",
    "polnum": "26735",
    "precinctsreporting": 59,
    "precinctsreportingpct": 1,
    "precinctstotal": 59,
    "raceid": "24012",
    "runoff": false,
    "seatnum": null,
    "statepostal": "MA",
    "votecount": 13469,
    "votepct": 0.251255,
    "winner": false
  },
  {
    "fipscode": "25003",
    "level": "county",
    "officeid": "S",
    "party": "Ind",
    "polid": "67866",
    "polnum": "27962",
    "precinctsreporting": 59,
    "precinctsreportingpct": 1,
    "precinctstotal": 59,
    "raceid": "24012",
    "runoff": false,
    "seatnum": null,
    "statepostal": "MA",
    "votecount": 1516,
    "votepct": 0.02828,
    "winner": false
  },
  {
    "fipscode": "25005",
    "level": "county",
    "officeid": "S",
    "party": "Dem",
    "polid": "62244",
    "polnum": "27010",
    "precinctsreporting": 172,
    "precinctsreportingpct": 1,
    "precinctstotal": 172,
    "raceid": "24012",
    "runoff": false,
    "seatnum": null,
    "statepostal": "MA",
    "votecount": 96763,
    "votepct": 0.520172,
    "winner": false
  },
  {
    "fipscode": "25005",
    "level": "county",
    "officeid": "S",
    "party": "GOP",
    "polid": "67466",
    "polnum": "26735",
    "precinctsreporting": 172,
    "precinctsreportingpct": 1,
    "precinctstotal": 172,
    "raceid": "24012",
    "runoff": false,
    "seatnum": null,
    "statepostal": "MA",
    "votecount": 82686,
    "votepct": 0.444498,
    "winner": false
  },
  {
    "fipscode": "25005",
    "level": "county",
    "officeid": "S",
    "party": "Ind",
    "polid": "67866",
    "polnum": "27962",
    "precinctsreporting": 172,
    "precinctsreportingpct": 1,
    "precinctstotal": 172,
    "raceid": "24012",
    "runoff": false,
    "seatnum": null,
    "statepostal": "MA",
    "votecount": 6572,
    "votepct": 0.035329,
    "winner": false
  },
  {
    "fipscode": "25007",
    "level": "county",
    "officeid": "S",
    "party": "Dem",
    "polid": "62244",
    "polnum": "27010",
    "precinctsreporting": 7,
    "precinctsreportingpct": 1,
    "precinctstotal": 7,
    "raceid": "24012",
    "runoff": false,
    "seatnum": null,
    "statepostal": "MA",
    "votecount": 7381,
    "votepct": 0.731371,
    "winner": false
  },
  {
    "fipscode": "25007",
    "level": "county",
    "officeid": "S",
    "party": "GOP",
    "polid": "67466",
    "polnum": "26735",
    "precinctsreporting": 7,
    "precinctsreportingpct": 1,
    "precinctstotal": 7,
    "raceid": "24012",
    "runoff": false,
    "seatnum": null,
    "statepostal": "MA",
    "votecount": 2331,
    "votepct": 0.230975,
    "winner": false
  },
  {
    "fipscode": "25007",
    "level": "county",
    "officeid": "S",
    "party": "Ind",
    "polid": "67866",
    "polnum": "27962",
    "precinctsreporting": 7,
    "precinctsreportingpct": 1,
    "precinctstotal": 7,
    "raceid": "24012",
    "runoff": false,
    "seatnum": null,
    "statepostal": "MA",
    "votecount": 380,
    "votepct": 0.037654,
    "winner": false
  },
  {
    "fipscode": "25009",
    "level": "county",
    "officeid": "S",
    "party": "Dem",
    "polid": "62244",
    "polnum": "27010",
    "precinctsreporting": 239,
    "precinctsreportingpct": 1,
    "precinctstotal": 239,
    "raceid": "24012",
    "runoff": false,
    "seatnum": null,
    "statepostal": "MA",
    "votecount": 176860,
    "votepct": 0.570452,
    "winner": false
  },
  {
    "fipscode": "25009",
    "level": "county",
    "officeid": "S",
    "party": "GOP",
    "polid": "67466",
    "polnum": "26735",
    "precinctsreporting": 239,
    "precinctsreportingpct": 1,
    "precinctstotal": 239,
    "raceid": "24012",
    "runoff": false,
    "seatnum": null,
    "statepostal": "MA",
    "votecount": 121456,
    "votepct": 0.391749,
    "winner": false
  },
  {
    "fipscode": "25009",
    "level": "county",
    "officeid": "S",
    "party": "Ind",
    "polid": "67866",
    "polnum": "27962",
    "precinctsreporting": 239,
    "precinctsreportingpct": 1,
    "precinctstotal": 239,
    "raceid": "24012",
    "runoff": false,
    "seatnum": null,
    "statepostal": "MA",
    "votecount": 11719,
    "votepct": 0.037799,
    "winner": false
  },
  {
    "fipscode": "25011",
    "level": "county",
    "officeid": "S",
    "party": "Dem",
    "polid": "62244",
    "polnum": "27010",
    "precinctsreporting": 40,
    "precinctsreportingpct": 1,
    "precinctstotal": 40,
    "raceid": "24012",
    "runoff": false,
    "seatnum": null,
    "statepostal": "MA",
    "votecount": 22847,
    "votepct": 0.694966,
    "winner": false
  },
  {
    "fipscode": "25011",
    "level": "county",
    "officeid": "S",
    "party": "GOP",
    "polid": "67466",
    "polnum": "26735",
    "precinctsreporting": 40,
    "precinctsreportingpct": 1,
    "precinctstotal": 40,
    "raceid": "24012",
    "runoff": false,
    "seatnum": null,
    "statepostal": "MA",
    "votecount": 8769,
    "votepct": 0.266738,
    "winner": false
  },
  {
    "fipscode": "25011",
    "level": "county",
    "officeid": "S",
    "party": "Ind",
    "polid": "67866",
    "polnum": "27962",
    "precinctsreporting": 40,
    "precinctsreportingpct": 1,
    "precinctstotal": 40,
    "raceid": "24012",
    "runoff": false,
    "seatnum": null,
    "statepostal": "MA",
    "votecount": 1259,
    "votepct": 0.038297,
    "winner": false
  },
  {
    "fipscode": "25013",
    "level": "county",
    "officeid": "S",
    "party": "Dem",
    "polid": "62244",
    "polnum": "27010",
    "precinctsreporting": 166,
    "precinctsreportingpct": 1,
    "precinctstotal": 166,
    "raceid": "24012",
    "runoff": false,
    "seatnum": null,
    "statepostal": "MA",
    "votecount": 86990,
    "votepct": 0.557954,
    "winner": false
  },
  {
    "fipscode": "25013",
    "level": "county",
    "officeid": "S",
    "party": "GOP",
    "polid": "67466",
    "polnum": "26735",
    "precinctsreporting": 166,
    "precinctsreportingpct": 1,
    "precinctstotal": 166,
    "raceid": "24012",
    "runoff": false,
    "seatnum": null,
    "statepostal": "MA",
    "votecount": 63046,
    "votepct": 0.404377,
    "winner": false
  },
  {
    "fipscode": "25013",
    "level": "county",
    "officeid": "S",
    "party": "Ind",
    "polid": "67866",
    "polnum": "27962",
    "precinctsreporting": 166,
    "precinctsreportingpct": 1,
    "precinctstotal": 166,
    "raceid": "24012",
    "runoff": false,
    "seatnum": null,
    "statepostal": "MA",
    "votecount": 5873,
    "votepct": 0.037669,
    "winner": false
  },
  {
    "fipscode": "25015",
    "level": "county",
    "officeid": "S",
    "party": "Dem",
    "polid": "62244",
    "polnum": "27010",
    "precinctsreporting": 56,
    "precinctsreportingpct": 1,
    "precinctstotal": 56,
    "raceid": "24012",
    "runoff": false,
    "seatnum": null,
    "statepostal": "MA",
    "votecount": 49552,
    "votepct": 0.705346,
    "winner": false
  },
  {
    "fipscode": "25015",
    "level": "county",
    "officeid": "S",
    "party": "GOP",
    "polid": "67466",
    "polnum": "26735",
    "precinctsreporting": 56,
    "precinctsreportingpct": 1,
    "precinctstotal": 56,
    "raceid": "24012",
    "runoff": false,
    "seatnum": null,
    "statepostal": "MA",
    "votecount": 18136,
    "votepct": 0.258156,
    "winner": false
  },
  {
    "fipscode": "25015",
    "level": "county",
    "officeid": "S",
    "party": "Ind",
    "polid": "67866",
    "polnum": "27962",
    "precinctsreporting": 56,
    "precinctsreportingpct": 1,
    "precinctstotal": 56,
    "raceid": "24012",
    "runoff": false,
    "seatnum": null,
    "statepostal": "MA",
    "votecount": 2564,
    "votepct": 0.036497,
    "winner": false
  },
  {
    "fipscode": "25017",
    "level": "county",
    "officeid": "S",
    "party": "Dem",
    "polid": "62244",
    "polnum": "27010",
    "precinctsreporting": 474,
    "precinctsreportingpct": 1,
    "precinctstotal": 474,
    "raceid": "24012",
    "runoff": false,
    "seatnum": null,
    "statepostal": "MA",
    "votecount": 435244,
    "votepct": 0.660625,
    "winner": false
  },
  {
    "fipscode": "25017",
    "level": "county",
    "officeid": "S",
    "party": "GOP",
    "polid": "67466",
    "polnum": "26735",
    "precinctsreporting": 474,
    "precinctsreportingpct": 1,
    "precinctstotal": 474,
    "raceid": "24012",
    "runoff": false,
    "seatnum": null,
    "statepostal": "MA",
    "votecount": 201160,
    "votepct": 0.305326,
    "winner": false
  },
  {
    "fipscode": "25017",
    "level": "county",
    "officeid": "S",
    "party": "Ind",
    "polid": "67866",
    "polnum": "27962",
    "precinctsreporting": 474,
    "precinctsreportingpct": 1,
    "precinctstotal": 474,
    "raceid": "24012",
    "runoff": false,
    "seatnum": null,
    "statepostal": "MA",
    "votecount": 22433,
    "votepct": 0.034049,
    "winner": false
  },
  {
    "fipscode": "25019",
    "level": "county",
    "officeid": "S",
    "party": "Dem",
    "polid": "62244",
    "polnum": "27010",
    "precinctsreporting": 1,
    "precinctsreportingpct": 1,
    "precinctstotal": 1,
    "raceid": "24012",
    "runoff": false,
    "seatnum": null,
    "statepostal": "MA",
    "votecount": 3504,
    "votepct": 0.659018,
    "winner": false
  },
  {
    "fipscode": "25019",
    "level": "county",
    "officeid": "S",
    "party": "GOP",
    "polid": "67466",
    "polnum": "26735",
    "precinctsreporting": 1,
    "precinctsreportingpct": 1,
    "precinctstotal": 1,
    "raceid": "24012",
    "runoff": false,
    "seatnum": null,
    "statepostal": "MA",
    "votecount": 1648,
    "votepct": 0.309949,
    "winner": false
  },
  {
    "fipscode": "25019",
    "level": "county",
    "officeid": "S",
    "party": "Ind",
    "polid": "67866",
    "polnum": "27962",
    "precinctsreporting": 1,
    "precinctsreportingpct": 1,
    "precinctstotal": 1,
    "raceid": "24012",
    "runoff": false,
    "seatnum": null,
    "statepostal": "MA",
    "votecount": 165,
    "votepct": 0.031033,
    "winner": false
  },
  {
    "fipscode": "25021",
    "level": "county",
    "officeid": "S",
    "party": "Dem",
    "polid": "62244",
    "polnum": "27010",
    "precinctsreporting": 211,
    "precinctsreportingpct": 1,
    "precinctstotal": 211,
    "raceid": "24012",
    "runoff": false,
    "seatnum": null,
    "statepostal": "MA",
    "votecount": 178051,
    "votepct": 0.585122,
    "winner": false
  },
  {
    "fipscode": "25021",
    "level": "county",
    "officeid": "S",
    "party": "GOP",
    "polid": "67466",
    "polnum": "26735",
    "precinctsreporting": 211,
    "precinctsreportingpct": 1,
    "precinctstotal": 211,
    "raceid": "24012",
    "runoff": false,
    "seatnum": null,
    "statepostal": "MA",
    "votecount": 116650,
    "votepct": 0.383343,
    "winner": false
  },
  {
    "fipscode": "25021",
    "level": "county",
    "officeid": "S",
    "party": "Ind",
    "polid": "67866",
    "polnum": "27962",
    "precinctsreporting": 211,
    "precinctsreportingpct": 1,
    "precinctstotal": 211,
    "raceid": "24012",
    "runoff": false,
    "seatnum": null,
    "statepostal": "MA",
    "votecount": 9596,
    "votepct": 0.031535,
    "winner": false
  },
  {
    "fipscode": "25023",
    "level": "county",
    "officeid": "S",
    "party": "Dem",
    "polid": "62244",
    "polnum": "27010",
    "precinctsreporting": 143,
    "precinctsreportingpct": 1,
    "precinctstotal": 143,
    "raceid": "24012",
    "runoff": false,
    "seatnum": null,
    "statepostal": "MA",
    "votecount": 106521,
    "votepct": 0.479213,
    "winner": false
  },
  {
    "fipscode": "25023",
    "level": "county",
    "officeid": "S",
    "party": "GOP",
    "polid": "67466",
    "polnum": "26735",
    "precinctsreporting": 143,
    "precinctsreportingpct": 1,
    "precinctstotal": 143,
    "raceid": "24012",
    "runoff": false,
    "seatnum": null,
    "statepostal": "MA",
    "votecount": 109329,
    "votepct": 0.491846,
    "winner": false
  },
  {
    "fipscode": "25023",
    "level": "county",
    "officeid": "S",
    "party": "Ind",
    "polid": "67866",
    "polnum": "27962",
    "precinctsreporting": 143,
    "precinctsreportingpct": 1,
    "precinctstotal": 143,
    "raceid": "24012",
    "runoff": false,
    "seatnum": null,
    "statepostal": "MA",
    "votecount": 6433,
    "votepct": 0.028941,
    "winner": false
  },
  {
    "fipscode": "25025",
    "level": "county",
    "officeid": "S",
    "party": "Dem",
    "polid": "62244",
    "polnum": "27010",
    "precinctsreporting": 298,
    "precinctsreportingpct": 1,
    "precinctstotal": 298,
    "raceid": "24012",
    "runoff": false,
    "seatnum": null,
    "statepostal": "MA",
    "votecount": 194008,
    "votepct": 0.787198,
    "winner": false
  },
  {
    "fipscode": "25025",
    "level": "county",
    "officeid": "S",
    "party": "GOP",
    "polid": "67466",
    "polnum": "26735",
    "precinctsreporting": 298,
    "precinctsreportingpct": 1,
    "precinctstotal": 298,
    "raceid": "24012",
    "runoff": false,
    "seatnum": null,
    "statepostal": "MA",
    "votecount": 46170,
    "votepct": 0.187337,
    "winner": false
  },
  {
    "fipscode": "25025",
    "level": "county",
    "officeid": "S",
    "party": "Ind",
    "polid": "67866",
    "polnum": "27962",
    "precinctsreporting": 298,
    "precinctsreportingpct": 1,
    "precinctstotal": 298,
    "raceid": "24012",
    "runoff": false,
    "seatnum": null,
    "statepostal": "MA",
    "votecount": 6276,
    "votepct": 0.025465,
    "winner": false
  },
  {
    "fipscode": "25027",
    "level": "county",
    "officeid": "S",
    "party": "Dem",
    "polid": "62244",
    "polnum": "27010",
    "precinctsreporting": 242,
    "precinctsreportingpct": 1,
    "precinctstotal": 242,
    "raceid": "24012",
    "runoff": false,
    "seatnum": null,
    "statepostal": "MA",
    "votecount": 158950,
    "votepct": 0.513565,
    "winner": false
  },
  {
    "fipscode": "25027",
    "level": "county",
    "officeid": "S",
    "party": "GOP",
    "polid": "67466",
    "polnum": "26735",
    "precinctsreporting": 242,
    "precinctsreportingpct": 1,
    "precinctstotal": 242,
    "raceid": "24012",
    "runoff": false,
    "seatnum": null,
    "statepostal": "MA",
    "votecount": 137860,
    "votepct": 0.445424,
    "winner": false
  },
  {
    "fipscode": "25027",
    "level": "county",
    "officeid": "S",
    "party": "Ind",
    "polid": "67866",
    "polnum": "27962",
    "precinctsreporting": 242,
    "precinctsreportingpct": 1,
    "precinctstotal": 242,
    "raceid": "24012",
    "runoff": false,
    "seatnum": null,
    "statepostal": "MA",
    "votecount": 12693,
    "votepct": 0.041011,
    "winner": false
  }
]
